asari/__init__.py
asari/analyze.py
asari/annotate_user_table.py
asari/chromatograms.py
asari/command_line.py
asari/constructors.py
asari/dashboard.py
asari/default_parameters.py
asari/experiment.py
asari/json_encoder.py
asari/main.py
asari/mass_functions.py
asari/peaks.py
asari/qc.py
asari/samples.py
asari/workflow.py
asari/db/__init__.py
asari/db/emp_cpds_trees.pickle
asari/db/mass_indexed_compounds.pickle
asari/tools/__init__.py
asari/tools/extract_masstracks.py
asari/tools/match_features.py
asari/tools/merge.py
asari/tools/plot.py
asari_metabolomics-1.13.1.data/data/asari/db/emp_cpds_trees.pickle
asari_metabolomics-1.13.1.data/data/asari/db/mass_indexed_compounds.pickle
asari_metabolomics-1.13.1.dist-info/LICENSE
asari_metabolomics-1.13.1.dist-info/METADATA
asari_metabolomics-1.13.1.dist-info/WHEEL
asari_metabolomics-1.13.1.dist-info/entry_points.txt
asari_metabolomics-1.13.1.dist-info/top_level.txt
asari_metabolomics-1.13.1.dist-info/zip-safe
asari_metabolomics-1.13.1.dist-info/RECORD
