Metadata-Version: 2.1
Name: asari-metabolomics
Version: 1.13.1
Summary: LC-MS metabolomics data preprocessing
Home-page: https://github.com/shuzhao-li/asari
Author: Shuzhao Li
Author-email: shuzhao.li@gmail.com
License: BSD 3-Clause
Keywords: metabolomics bioinformatics mass spectrometry
Classifier: Intended Audience :: Developers
Classifier: Intended Audience :: Science/Research
Classifier: License :: OSI Approved :: BSD License
Classifier: Natural Language :: English
Classifier: Operating System :: OS Independent
Classifier: Programming Language :: Python :: 3
Classifier: Topic :: Scientific/Engineering :: Bio-Informatics
Classifier: Topic :: Scientific/Engineering :: Chemistry
Classifier: Topic :: Software Development :: Libraries :: Python Modules
Requires-Python: >=3.7
License-File: LICENSE
Requires-Dist: metDatamodel
Requires-Dist: mass2chem
Requires-Dist: khipu-metabolomics >=0.7.0
Requires-Dist: jms-metabolite-services >=0.5.7
Requires-Dist: pymzml
Requires-Dist: numpy
Requires-Dist: scipy
Requires-Dist: statsmodels
Requires-Dist: pyyaml
Requires-Dist: panel >=0.13.0
Requires-Dist: holoviews
Requires-Dist: hvplot
Requires-Dist: seaborn
Requires-Dist: matplotlib
